stockaid/LSTM.py
stockaid/TDA.py
stockaid/__init__.py
stockaid/cache.py
stockaid/future_algo.py
stockaid/index.py
stockaid/MiniZinc/__init__.py
stockaid/greeks/__init__.py
stockaid/logging/__init__.py
stockaid/throttle/__init__.py
stockaid-0.2.dist-info/LICENSE
stockaid-0.2.dist-info/WHEEL
stockaid-0.2.dist-info/METADATA
stockaid-0.2.dist-info/RECORD
